openqaoa_pyquil/__init__.py
openqaoa_pyquil/_version.py
openqaoa_pyquil/backend_config.py
openqaoa_pyquil/backends/__init__.py
openqaoa_pyquil/backends/devices.py
openqaoa_pyquil/backends/gates_pyquil.py
openqaoa_pyquil/backends/qaoa_pyquil_qpu.py
openqaoa_pyquil/backends/qaoa_pyquil_sim.py
openqaoa_pyquil-0.2.6.dist-info/LICENSE
openqaoa_pyquil-0.2.6.dist-info/METADATA
openqaoa_pyquil-0.2.6.dist-info/WHEEL
openqaoa_pyquil-0.2.6.dist-info/entry_points.txt
openqaoa_pyquil-0.2.6.dist-info/top_level.txt
openqaoa_pyquil-0.2.6.dist-info/RECORD
